capyslay/__init__.py
capyslay/calculator.py
capyslay/caller.py
capyslay/code.py
capyslay/corpus.py
capyslay/counter.py
capyslay/currencyConverter.py
capyslay/database1.py
capyslay/grams.py
capyslay/mediaplayer.py
capyslay/module1.py
capyslay/module2.py
capyslay/pos.py
capyslay/quiz.py
capyslay/signin.py
capyslay/smoothing.py
capyslay/stemming.py
capyslay/stopwords.py
capyslay/studData.py
capyslay/text2speech.py
capyslay/tokenizer.py
capyslay/unitsConverter.py
capyslay/visitingCard.py
capyslay/wallpaper.py
capyslay/wordcount.py
capyslay-0.6.0.dist-info/METADATA
capyslay-0.6.0.dist-info/WHEEL
capyslay-0.6.0.dist-info/top_level.txt
capyslay-0.6.0.dist-info/RECORD
