Metadata-Version: 2.2
Name: capyslay
Version: 0.6.0
Summary: A sample Python package
Author-email: Capy Bara <capyslayers@gmail.com>
Requires-Dist: IPython
